[
  {
    "id": 1,
    "name": "Men's Casual T-Shirt",
    "image": "https://via.placeholder.com/400x300",
    "desc": "Soft cotton t-shirt perfect for everyday wear.",
    "price": 12.99
  },
  {
    "id": 2,
    "name": "Women's Summer Dress",
    "image": "https://via.placeholder.com/400x300",
    "desc": "Lightweight floral dress ideal for warm weather.",
    "price": 24.99
  },
  {
    "id": 3,
    "name": "Men's Denim Jacket",
    "image": "https://via.placeholder.com/400x300",
    "desc": "Classic denim jacket with a modern fit.",
    "price": 39.99
  },
  {
    "id": 4,
    "name": "Women's Hoodie",
    "image": "https://via.placeholder.com/400x300",
    "desc": "Comfortable fleece hoodie for casual wear.",
    "price": 19.99
  },
  {
    "id": 5,
    "name": "Kids' Printed T-Shirt",
    "image": "https://via.placeholder.com/400x300",
    "desc": "Cute and colorful printed tee for kids.",
    "price": 8.99
  },
  {
    "id": 6,
    "name": "Men's Formal Shirt",
    "image": "https://via.placeholder.com/400x300",
    "desc": "Premium cotton formal shirt for office wear.",
    "price": 18.99
  }
]
